natf/__init__.py
natf/cell.py
natf/fispact_input.py
natf/fispact_output.py
natf/half_space.py
natf/material.py
natf/mcnp_input.py
natf/mcnp_output.py
natf/mesh.py
natf/natf_functions.py
natf/nuc_treat.py
natf/part.py
natf/plot.py
natf/radwaste_standard.py
natf/settings.py
natf/source_particle.py
natf/surface.py
natf/utils.py
natf/version
natf/data/README.md
natf/data/appendix16
natf/data/fendl31c_nucs
natf/data/tendl19c_nucs
natf/data/ebins/ebins_100
natf/data/ebins/ebins_1102
natf/data/ebins/ebins_162
natf/data/ebins/ebins_172
natf/data/ebins/ebins_175
natf/data/ebins/ebins_211
natf/data/ebins/ebins_24
natf/data/ebins/ebins_315
natf/data/ebins/ebins_351
natf/data/ebins/ebins_586
natf/data/ebins/ebins_616
natf/data/ebins/ebins_66
natf/data/ebins/ebins_69
natf/data/ebins/ebins_709
natf/data/fispact_files/FILES-175
natf/data/fispact_files/FILES-709
natf/data/fluence_to_dose_factors/README.md
natf/data/fluence_to_dose_factors/ch2_neutron_iter.csv
natf/data/fluence_to_dose_factors/silicon_neutron_iter.csv
natf/data/fluence_to_dose_factors/tissue_neutron_icrp_116.csv
natf/data/fluence_to_dose_factors/tissue_photon_icrp_116.csv
natf/radwaste_standards/CHN2018/CHN2018.csv
natf/radwaste_standards/D-VALUES/dvalues_iaea_2006.csv
natf/radwaste_standards/FRANCE/TFA.csv
natf/radwaste_standards/RUSSIAN/RUSSIAN.csv
natf/radwaste_standards/USNRC/README.md
natf/radwaste_standards/USNRC/USNRC_EDE_MASS.csv
natf/radwaste_standards/USNRC/USNRC_LL.csv
natf/radwaste_standards/USNRC/USNRC_SL.csv
natf/radwaste_standards/USNRC_FETTER/USNRC_FETTER.csv
natf-3.7.0.dist-info/METADATA
natf-3.7.0.dist-info/WHEEL
natf-3.7.0.dist-info/entry_points.txt
natf-3.7.0.dist-info/top_level.txt
natf-3.7.0.dist-info/RECORD
