Metadata-Version: 2.4
Name: natf
Version: 3.7.0
Summary: Nuclear Analysis toolkit for Fusion with coupling of MCNP and FISPACT
Home-page: https://github.com/zxkjack123/NATF
Author: Xiaokang Zhang
Author-email: zxkjack123@163.com
License: MIT
Classifier: Programming Language :: Python :: 3
Classifier: License :: OSI Approved :: MIT License
Classifier: Operating System :: OS Independent
Classifier: Environment :: Console
Requires-Python: >=3.6
Dynamic: author
Dynamic: author-email
Dynamic: classifier
Dynamic: description
Dynamic: description-content-type
Dynamic: home-page
Dynamic: license
Dynamic: requires-python
Dynamic: summary
